systemtools/__init__.py
systemtools/checktcpconn.py
systemtools/commandpath.py
systemtools/escape.py
systemtools/flock.py
systemtools/linkidentical.py
systemtools/pidutil.py
systemtools/progressbar.py
systemtools/rglob.py
systemtools/shuffle.py
systemtools/sizestr.py
systemtools/sortedlist.py
systemtools/syslogger.py
systemtools/systemstats.py
systemtools/toposort.py
systemtools/userinput.py
systemtools-1.0.1.dist-info/top_level.txt
systemtools-1.0.1.dist-info/METADATA
systemtools-1.0.1.dist-info/zip-safe
systemtools-1.0.1.dist-info/DESCRIPTION.rst
systemtools-1.0.1.dist-info/metadata.json
systemtools-1.0.1.dist-info/WHEEL
systemtools-1.0.1.dist-info/RECORD
