Metadata-Version: 2.0
Name: systemtools
Version: 1.0.1
Summary: systools: System utility modules
Home-page: https://github.com/gammazero/systemtools
Author: Andrew Gillis
Author-email: gillis.andrewj@gmail.com
License: http://www.opensource.org/licenses/mit-license.php
Keywords: system CLI utility
Platform: unix
Platform: linux
Platform: cygwin
Classifier: Development Status :: 5 - Production/Stable
Classifier: Intended Audience :: Developers
Classifier: License :: OSI Approved :: MIT License
Classifier: Operating System :: POSIX
Classifier: Topic :: Software Development :: Libraries
Classifier: Topic :: Utilities
Classifier: Programming Language :: Python
Classifier: Programming Language :: Python :: 2.7
Classifier: Programming Language :: Python :: 3
